<summarization>
<time_segment>
<start_time>81</start_time>
<end_time>160</end_time>
<totalsegmentcost>13508.518555</totalsegmentcost>
<local_segment>
<event_id>48</event_id>
<event_id>1</event_id>
<event_id>2</event_id>
<event_id>3</event_id>
<event_id>7</event_id>
<event_id>8</event_id>
<event_id>10</event_id>
<event_id>11</event_id>
<event_id>12</event_id>
<event_id>14</event_id>
<event_id>15</event_id>
<event_id>16</event_id>
<event_id>17</event_id>
<event_id>18</event_id>
<event_id>20</event_id>
<event_id>21</event_id>
<event_id>22</event_id>
<event_id>24</event_id>
<event_id>27</event_id>
<event_id>28</event_id>
<event_id>29</event_id>
<event_id>30</event_id>
<event_id>31</event_id>
<event_id>32</event_id>
<event_id>33</event_id>
<event_id>34</event_id>
<event_id>35</event_id>
<event_id>36</event_id>
<event_id>37</event_id>
<event_id>38</event_id>
<event_id>39</event_id>
<event_id>41</event_id>
<event_id>42</event_id>
<event_id>45</event_id>
<event_id>46</event_id>
<event_id>47</event_id>
<event_id>50</event_id>
<event_id>52</event_id>
<event_id>53</event_id>
<event_id>54</event_id>
<event_id>57</event_id>
<event_id>58</event_id>
<event_id>59</event_id>
<event_id>62</event_id>
<event_id>64</event_id>
<event_id>65</event_id>
<event_id>66</event_id>
<event_id>68</event_id>
<event_id>71</event_id>
<event_id>73</event_id>
<event_id>74</event_id>
<event_id>75</event_id>
<event_id>77</event_id>
<event_id>82</event_id>
<event_id>83</event_id>
<event_id>84</event_id>
<event_id>85</event_id>
<event_id>90</event_id>
<event_id>91</event_id>
<event_id>92</event_id>
<event_id>96</event_id>
<event_id>97</event_id>
<event_id>98</event_id>
<event_id>101</event_id>
<event_id>102</event_id>
<event_id>104</event_id>
<event_id>105</event_id>
<event_id>106</event_id>
<event_id>108</event_id>
<event_id>109</event_id>
<event_id>111</event_id>
<event_id>112</event_id>
<event_id>117</event_id>
<event_id>118</event_id>
<event_id>120</event_id>
<event_id>121</event_id>
<event_id>123</event_id>
<event_id>125</event_id>
<event_id>129</event_id>
<event_id>130</event_id>
<event_id>131</event_id>
<event_id>132</event_id>
<event_id>134</event_id>
<event_id>135</event_id>
<event_id>136</event_id>
<event_id>137</event_id>
<event_id>138</event_id>
<event_id>140</event_id>
<event_id>141</event_id>
<event_id>143</event_id>
<event_id>145</event_id>
<event_id>146</event_id>
<event_id>148</event_id>
<event_id>150</event_id>
<event_id>63</event_id>
<event_id>23</event_id>
<event_id>72</event_id>
<event_id>25</event_id>
<event_id>70</event_id>
<event_id>4</event_id>
<event_id>43</event_id>
<event_id>61</event_id>
<event_id>78</event_id>
<event_id>55</event_id>
<event_id>126</event_id>
<event_id>128</event_id>
<event_id>44</event_id>
<event_id>69</event_id>
<event_id>86</event_id>
<event_id>119</event_id>
<event_id>19</event_id>
<event_id>51</event_id>
<event_id>81</event_id>
<event_id>115</event_id>
<event_id>122</event_id>
<event_id>124</event_id>
<event_id>9</event_id>
<event_id>149</event_id>
<event_id>40</event_id>
<event_id>87</event_id>
<event_id>144</event_id>
<event_id>76</event_id>
<event_id>110</event_id>
<event_id>133</event_id>
<event_id>142</event_id>
<event_id>5</event_id>
<event_id>6</event_id>
<event_id>94</event_id>
<event_id>114</event_id>
<event_id>13</event_id>
<event_id>49</event_id>
<event_id>93</event_id>
<event_id>95</event_id>
<event_id>100</event_id>
<event_id>107</event_id>
<event_id>113</event_id>
<event_id>127</event_id>
<event_id>139</event_id>
<event_id>26</event_id>
<event_id>60</event_id>
<event_id>67</event_id>
<event_id>89</event_id>
<event_id>80</event_id>
<event_id>79</event_id>
<event_id>103</event_id>
<event_id>56</event_id>
<event_id>88</event_id>
<event_id>99</event_id>
<event_id>116</event_id>
<event_id>147</event_id>
<dailyrate>1.207333</dailyrate>
<cost>12751.836914</cost>
</local_segment>
<segmentcost>756.670468</segmentcost>
</time_segment>
<time_segment>
<start_time>71</start_time>
<end_time>80</end_time>
<totalsegmentcost>4269.588379</totalsegmentcost>
<local_segment>
<event_id>61</event_id>
<event_id>98</event_id>
<event_id>64</event_id>
<event_id>92</event_id>
<event_id>59</event_id>
<event_id>99</event_id>
<event_id>88</event_id>
<event_id>93</event_id>
<event_id>95</event_id>
<event_id>97</event_id>
<event_id>53</event_id>
<event_id>70</event_id>
<event_id>81</event_id>
<event_id>86</event_id>
<event_id>51</event_id>
<event_id>67</event_id>
<event_id>68</event_id>
<event_id>87</event_id>
<event_id>91</event_id>
<event_id>52</event_id>
<event_id>55</event_id>
<event_id>60</event_id>
<event_id>63</event_id>
<event_id>73</event_id>
<event_id>76</event_id>
<event_id>77</event_id>
<event_id>82</event_id>
<event_id>85</event_id>
<event_id>96</event_id>
<event_id>100</event_id>
<event_id>54</event_id>
<event_id>57</event_id>
<event_id>65</event_id>
<event_id>89</event_id>
<event_id>62</event_id>
<event_id>72</event_id>
<event_id>75</event_id>
<event_id>79</event_id>
<event_id>80</event_id>
<event_id>84</event_id>
<event_id>66</event_id>
<event_id>74</event_id>
<event_id>78</event_id>
<event_id>83</event_id>
<event_id>90</event_id>
<event_id>56</event_id>
<event_id>58</event_id>
<event_id>69</event_id>
<event_id>94</event_id>
<event_id>71</event_id>
<dailyrate>1.006000</dailyrate>
<cost>556.279297</cost>
</local_segment>
<local_segment>
<event_id>144</event_id>
<event_id>104</event_id>
<event_id>125</event_id>
<event_id>122</event_id>
<event_id>121</event_id>
<event_id>136</event_id>
<event_id>106</event_id>
<event_id>149</event_id>
<event_id>105</event_id>
<event_id>127</event_id>
<event_id>134</event_id>
<event_id>111</event_id>
<event_id>115</event_id>
<event_id>131</event_id>
<event_id>103</event_id>
<event_id>118</event_id>
<event_id>112</event_id>
<event_id>132</event_id>
<event_id>130</event_id>
<event_id>124</event_id>
<event_id>126</event_id>
<event_id>114</event_id>
<event_id>133</event_id>
<event_id>148</event_id>
<event_id>113</event_id>
<event_id>138</event_id>
<event_id>109</event_id>
<event_id>143</event_id>
<event_id>150</event_id>
<event_id>137</event_id>
<event_id>135</event_id>
<event_id>107</event_id>
<event_id>146</event_id>
<event_id>145</event_id>
<event_id>101</event_id>
<event_id>108</event_id>
<event_id>141</event_id>
<event_id>102</event_id>
<event_id>119</event_id>
<event_id>139</event_id>
<event_id>120</event_id>
<event_id>116</event_id>
<event_id>147</event_id>
<event_id>117</event_id>
<event_id>128</event_id>
<event_id>142</event_id>
<event_id>140</event_id>
<event_id>110</event_id>
<event_id>129</event_id>
<event_id>123</event_id>
<dailyrate>25.174000</dailyrate>
<cost>1344.183350</cost>
</local_segment>
<local_segment>
<event_id>20</event_id>
<event_id>38</event_id>
<event_id>48</event_id>
<event_id>23</event_id>
<event_id>37</event_id>
<event_id>32</event_id>
<event_id>35</event_id>
<event_id>1</event_id>
<event_id>7</event_id>
<event_id>6</event_id>
<event_id>36</event_id>
<event_id>5</event_id>
<event_id>12</event_id>
<event_id>17</event_id>
<event_id>31</event_id>
<event_id>42</event_id>
<event_id>39</event_id>
<event_id>9</event_id>
<event_id>8</event_id>
<event_id>50</event_id>
<event_id>11</event_id>
<event_id>16</event_id>
<event_id>19</event_id>
<event_id>43</event_id>
<event_id>24</event_id>
<event_id>44</event_id>
<event_id>26</event_id>
<event_id>28</event_id>
<event_id>34</event_id>
<event_id>4</event_id>
<event_id>14</event_id>
<event_id>46</event_id>
<event_id>25</event_id>
<event_id>29</event_id>
<event_id>40</event_id>
<event_id>22</event_id>
<event_id>10</event_id>
<event_id>45</event_id>
<event_id>27</event_id>
<event_id>41</event_id>
<event_id>33</event_id>
<event_id>13</event_id>
<event_id>18</event_id>
<event_id>21</event_id>
<event_id>3</event_id>
<event_id>30</event_id>
<event_id>2</event_id>
<event_id>49</event_id>
<event_id>15</event_id>
<event_id>47</event_id>
<dailyrate>76.003998</dailyrate>
<cost>1612.462891</cost>
</local_segment>
<segmentcost>756.670468</segmentcost>
</time_segment>
<time_segment>
<start_time>46</start_time>
<end_time>70</end_time>
<totalsegmentcost>8656.831055</totalsegmentcost>
<local_segment>
<event_id>101</event_id>
<event_id>143</event_id>
<event_id>128</event_id>
<event_id>117</event_id>
<event_id>129</event_id>
<event_id>118</event_id>
<event_id>146</event_id>
<event_id>133</event_id>
<event_id>106</event_id>
<event_id>135</event_id>
<event_id>139</event_id>
<event_id>148</event_id>
<event_id>115</event_id>
<event_id>116</event_id>
<event_id>122</event_id>
<event_id>123</event_id>
<event_id>150</event_id>
<event_id>104</event_id>
<event_id>119</event_id>
<event_id>120</event_id>
<event_id>121</event_id>
<event_id>137</event_id>
<event_id>145</event_id>
<event_id>125</event_id>
<event_id>132</event_id>
<event_id>114</event_id>
<event_id>124</event_id>
<event_id>127</event_id>
<event_id>105</event_id>
<event_id>107</event_id>
<event_id>126</event_id>
<event_id>130</event_id>
<event_id>131</event_id>
<event_id>142</event_id>
<event_id>103</event_id>
<event_id>136</event_id>
<event_id>144</event_id>
<event_id>147</event_id>
<event_id>109</event_id>
<event_id>110</event_id>
<event_id>138</event_id>
<event_id>141</event_id>
<event_id>102</event_id>
<event_id>113</event_id>
<event_id>108</event_id>
<event_id>111</event_id>
<event_id>112</event_id>
<event_id>149</event_id>
<event_id>140</event_id>
<event_id>134</event_id>
<dailyrate>1.036000</dailyrate>
<cost>1400.419434</cost>
</local_segment>
<local_segment>
<event_id>25</event_id>
<event_id>55</event_id>
<event_id>83</event_id>
<event_id>38</event_id>
<event_id>23</event_id>
<event_id>15</event_id>
<event_id>4</event_id>
<event_id>88</event_id>
<event_id>46</event_id>
<event_id>57</event_id>
<event_id>43</event_id>
<event_id>19</event_id>
<event_id>80</event_id>
<event_id>6</event_id>
<event_id>89</event_id>
<event_id>97</event_id>
<event_id>78</event_id>
<event_id>17</event_id>
<event_id>22</event_id>
<event_id>71</event_id>
<event_id>79</event_id>
<event_id>5</event_id>
<event_id>7</event_id>
<event_id>92</event_id>
<event_id>45</event_id>
<event_id>77</event_id>
<event_id>87</event_id>
<event_id>93</event_id>
<event_id>70</event_id>
<event_id>21</event_id>
<event_id>59</event_id>
<event_id>60</event_id>
<event_id>2</event_id>
<event_id>49</event_id>
<event_id>90</event_id>
<event_id>16</event_id>
<event_id>52</event_id>
<event_id>35</event_id>
<event_id>37</event_id>
<event_id>11</event_id>
<event_id>13</event_id>
<event_id>14</event_id>
<event_id>31</event_id>
<event_id>36</event_id>
<event_id>48</event_id>
<event_id>64</event_id>
<event_id>81</event_id>
<event_id>26</event_id>
<event_id>85</event_id>
<event_id>24</event_id>
<event_id>29</event_id>
<event_id>12</event_id>
<event_id>95</event_id>
<event_id>40</event_id>
<event_id>61</event_id>
<event_id>91</event_id>
<event_id>58</event_id>
<event_id>42</event_id>
<event_id>53</event_id>
<event_id>66</event_id>
<event_id>84</event_id>
<event_id>98</event_id>
<event_id>69</event_id>
<event_id>62</event_id>
<event_id>41</event_id>
<event_id>56</event_id>
<event_id>68</event_id>
<event_id>76</event_id>
<event_id>28</event_id>
<event_id>74</event_id>
<event_id>27</event_id>
<event_id>63</event_id>
<event_id>1</event_id>
<event_id>39</event_id>
<event_id>100</event_id>
<event_id>65</event_id>
<event_id>86</event_id>
<event_id>44</event_id>
<event_id>10</event_id>
<event_id>20</event_id>
<event_id>32</event_id>
<event_id>51</event_id>
<event_id>9</event_id>
<event_id>75</event_id>
<event_id>67</event_id>
<event_id>50</event_id>
<event_id>82</event_id>
<event_id>33</event_id>
<event_id>73</event_id>
<event_id>3</event_id>
<event_id>72</event_id>
<event_id>18</event_id>
<event_id>47</event_id>
<event_id>94</event_id>
<event_id>54</event_id>
<event_id>34</event_id>
<event_id>96</event_id>
<event_id>8</event_id>
<event_id>99</event_id>
<event_id>30</event_id>
<dailyrate>24.959600</dailyrate>
<cost>6499.758301</cost>
</local_segment>
<segmentcost>756.670468</segmentcost>
</time_segment>
<time_segment>
<start_time>26</start_time>
<end_time>45</end_time>
<totalsegmentcost>10167.068359</totalsegmentcost>
<local_segment>
<event_id>52</event_id>
<event_id>33</event_id>
<event_id>80</event_id>
<event_id>74</event_id>
<event_id>97</event_id>
<event_id>140</event_id>
<event_id>5</event_id>
<event_id>38</event_id>
<event_id>87</event_id>
<event_id>49</event_id>
<event_id>34</event_id>
<event_id>50</event_id>
<event_id>147</event_id>
<event_id>4</event_id>
<event_id>143</event_id>
<event_id>94</event_id>
<event_id>114</event_id>
<event_id>124</event_id>
<event_id>72</event_id>
<event_id>10</event_id>
<event_id>107</event_id>
<event_id>69</event_id>
<event_id>8</event_id>
<event_id>31</event_id>
<event_id>90</event_id>
<event_id>121</event_id>
<event_id>136</event_id>
<event_id>64</event_id>
<event_id>139</event_id>
<event_id>96</event_id>
<event_id>7</event_id>
<event_id>112</event_id>
<event_id>42</event_id>
<event_id>60</event_id>
<event_id>68</event_id>
<event_id>1</event_id>
<event_id>3</event_id>
<event_id>133</event_id>
<event_id>145</event_id>
<event_id>148</event_id>
<event_id>20</event_id>
<event_id>85</event_id>
<event_id>47</event_id>
<event_id>77</event_id>
<event_id>6</event_id>
<event_id>63</event_id>
<event_id>65</event_id>
<event_id>103</event_id>
<event_id>109</event_id>
<event_id>125</event_id>
<event_id>132</event_id>
<event_id>86</event_id>
<event_id>79</event_id>
<event_id>14</event_id>
<event_id>23</event_id>
<event_id>117</event_id>
<event_id>122</event_id>
<event_id>2</event_id>
<event_id>92</event_id>
<event_id>100</event_id>
<event_id>58</event_id>
<event_id>83</event_id>
<event_id>84</event_id>
<event_id>119</event_id>
<event_id>126</event_id>
<event_id>116</event_id>
<event_id>32</event_id>
<event_id>26</event_id>
<event_id>78</event_id>
<event_id>88</event_id>
<event_id>120</event_id>
<event_id>75</event_id>
<event_id>98</event_id>
<event_id>35</event_id>
<event_id>54</event_id>
<event_id>118</event_id>
<event_id>123</event_id>
<event_id>127</event_id>
<event_id>130</event_id>
<event_id>70</event_id>
<event_id>66</event_id>
<event_id>73</event_id>
<event_id>138</event_id>
<event_id>28</event_id>
<event_id>115</event_id>
<event_id>89</event_id>
<event_id>11</event_id>
<event_id>71</event_id>
<event_id>81</event_id>
<event_id>149</event_id>
<event_id>111</event_id>
<event_id>12</event_id>
<event_id>25</event_id>
<event_id>48</event_id>
<event_id>135</event_id>
<event_id>106</event_id>
<event_id>142</event_id>
<event_id>22</event_id>
<event_id>141</event_id>
<event_id>46</event_id>
<event_id>59</event_id>
<event_id>105</event_id>
<event_id>131</event_id>
<event_id>19</event_id>
<event_id>91</event_id>
<event_id>150</event_id>
<event_id>13</event_id>
<event_id>29</event_id>
<event_id>82</event_id>
<event_id>128</event_id>
<event_id>146</event_id>
<event_id>144</event_id>
<event_id>129</event_id>
<event_id>18</event_id>
<event_id>93</event_id>
<event_id>55</event_id>
<event_id>101</event_id>
<event_id>56</event_id>
<event_id>95</event_id>
<event_id>51</event_id>
<event_id>62</event_id>
<event_id>24</event_id>
<event_id>67</event_id>
<event_id>110</event_id>
<event_id>43</event_id>
<event_id>76</event_id>
<event_id>36</event_id>
<event_id>27</event_id>
<event_id>102</event_id>
<event_id>99</event_id>
<event_id>39</event_id>
<event_id>108</event_id>
<event_id>15</event_id>
<event_id>134</event_id>
<event_id>9</event_id>
<event_id>45</event_id>
<event_id>61</event_id>
<event_id>17</event_id>
<event_id>41</event_id>
<event_id>21</event_id>
<event_id>104</event_id>
<event_id>44</event_id>
<event_id>53</event_id>
<event_id>16</event_id>
<event_id>57</event_id>
<event_id>30</event_id>
<event_id>113</event_id>
<event_id>40</event_id>
<event_id>137</event_id>
<event_id>37</event_id>
<dailyrate>75.018333</dailyrate>
<cost>9410.465820</cost>
</local_segment>
<segmentcost>756.670468</segmentcost>
</time_segment>
<time_segment>
<start_time>16</start_time>
<end_time>25</end_time>
<totalsegmentcost>4287.649902</totalsegmentcost>
<local_segment>
<event_id>76</event_id>
<event_id>71</event_id>
<event_id>67</event_id>
<event_id>70</event_id>
<event_id>87</event_id>
<event_id>63</event_id>
<event_id>72</event_id>
<event_id>75</event_id>
<event_id>68</event_id>
<event_id>83</event_id>
<event_id>86</event_id>
<event_id>99</event_id>
<event_id>54</event_id>
<event_id>57</event_id>
<event_id>62</event_id>
<event_id>90</event_id>
<event_id>91</event_id>
<event_id>95</event_id>
<event_id>96</event_id>
<event_id>52</event_id>
<event_id>55</event_id>
<event_id>58</event_id>
<event_id>60</event_id>
<event_id>66</event_id>
<event_id>69</event_id>
<event_id>77</event_id>
<event_id>84</event_id>
<event_id>93</event_id>
<event_id>94</event_id>
<event_id>56</event_id>
<event_id>61</event_id>
<event_id>73</event_id>
<event_id>78</event_id>
<event_id>85</event_id>
<event_id>92</event_id>
<event_id>100</event_id>
<event_id>53</event_id>
<event_id>59</event_id>
<event_id>79</event_id>
<event_id>82</event_id>
<event_id>88</event_id>
<event_id>98</event_id>
<event_id>64</event_id>
<event_id>74</event_id>
<event_id>97</event_id>
<event_id>65</event_id>
<event_id>80</event_id>
<event_id>89</event_id>
<event_id>51</event_id>
<event_id>81</event_id>
<dailyrate>1.092000</dailyrate>
<cost>569.381470</cost>
</local_segment>
<local_segment>
<event_id>133</event_id>
<event_id>124</event_id>
<event_id>140</event_id>
<event_id>106</event_id>
<event_id>112</event_id>
<event_id>147</event_id>
<event_id>145</event_id>
<event_id>148</event_id>
<event_id>119</event_id>
<event_id>113</event_id>
<event_id>118</event_id>
<event_id>123</event_id>
<event_id>126</event_id>
<event_id>110</event_id>
<event_id>125</event_id>
<event_id>132</event_id>
<event_id>149</event_id>
<event_id>117</event_id>
<event_id>142</event_id>
<event_id>101</event_id>
<event_id>103</event_id>
<event_id>129</event_id>
<event_id>135</event_id>
<event_id>107</event_id>
<event_id>127</event_id>
<event_id>109</event_id>
<event_id>121</event_id>
<event_id>102</event_id>
<event_id>136</event_id>
<event_id>146</event_id>
<event_id>150</event_id>
<event_id>111</event_id>
<event_id>120</event_id>
<event_id>144</event_id>
<event_id>137</event_id>
<event_id>134</event_id>
<event_id>139</event_id>
<event_id>115</event_id>
<event_id>131</event_id>
<event_id>141</event_id>
<event_id>143</event_id>
<event_id>116</event_id>
<event_id>138</event_id>
<event_id>104</event_id>
<event_id>108</event_id>
<event_id>130</event_id>
<event_id>128</event_id>
<event_id>105</event_id>
<event_id>122</event_id>
<event_id>114</event_id>
<dailyrate>24.978001</dailyrate>
<cost>1347.984131</cost>
</local_segment>
<local_segment>
<event_id>4</event_id>
<event_id>14</event_id>
<event_id>9</event_id>
<event_id>19</event_id>
<event_id>31</event_id>
<event_id>44</event_id>
<event_id>41</event_id>
<event_id>24</event_id>
<event_id>28</event_id>
<event_id>27</event_id>
<event_id>36</event_id>
<event_id>49</event_id>
<event_id>25</event_id>
<event_id>33</event_id>
<event_id>45</event_id>
<event_id>1</event_id>
<event_id>12</event_id>
<event_id>22</event_id>
<event_id>37</event_id>
<event_id>23</event_id>
<event_id>43</event_id>
<event_id>38</event_id>
<event_id>32</event_id>
<event_id>29</event_id>
<event_id>18</event_id>
<event_id>16</event_id>
<event_id>30</event_id>
<event_id>10</event_id>
<event_id>35</event_id>
<event_id>39</event_id>
<event_id>26</event_id>
<event_id>7</event_id>
<event_id>13</event_id>
<event_id>40</event_id>
<event_id>47</event_id>
<event_id>48</event_id>
<event_id>2</event_id>
<event_id>21</event_id>
<event_id>8</event_id>
<event_id>46</event_id>
<event_id>34</event_id>
<event_id>3</event_id>
<event_id>42</event_id>
<event_id>20</event_id>
<event_id>50</event_id>
<event_id>17</event_id>
<event_id>6</event_id>
<event_id>11</event_id>
<event_id>15</event_id>
<event_id>5</event_id>
<dailyrate>74.683998</dailyrate>
<cost>1613.611572</cost>
</local_segment>
<segmentcost>756.670468</segmentcost>
</time_segment>
<time_segment>
<start_time>1</start_time>
<end_time>15</end_time>
<totalsegmentcost>6011.730957</totalsegmentcost>
<local_segment>
<event_id>1</event_id>
<event_id>25</event_id>
<event_id>23</event_id>
<event_id>16</event_id>
<event_id>29</event_id>
<event_id>31</event_id>
<event_id>42</event_id>
<event_id>43</event_id>
<event_id>45</event_id>
<event_id>9</event_id>
<event_id>13</event_id>
<event_id>18</event_id>
<event_id>22</event_id>
<event_id>26</event_id>
<event_id>30</event_id>
<event_id>39</event_id>
<event_id>7</event_id>
<event_id>21</event_id>
<event_id>35</event_id>
<event_id>38</event_id>
<event_id>3</event_id>
<event_id>6</event_id>
<event_id>36</event_id>
<event_id>46</event_id>
<event_id>10</event_id>
<event_id>12</event_id>
<event_id>20</event_id>
<event_id>11</event_id>
<event_id>14</event_id>
<event_id>17</event_id>
<event_id>19</event_id>
<event_id>37</event_id>
<event_id>50</event_id>
<event_id>2</event_id>
<event_id>34</event_id>
<event_id>4</event_id>
<event_id>5</event_id>
<event_id>24</event_id>
<event_id>27</event_id>
<event_id>28</event_id>
<event_id>44</event_id>
<event_id>49</event_id>
<event_id>41</event_id>
<event_id>33</event_id>
<event_id>47</event_id>
<event_id>8</event_id>
<event_id>15</event_id>
<event_id>32</event_id>
<event_id>40</event_id>
<event_id>48</event_id>
<dailyrate>1.018667</dailyrate>
<cost>836.622192</cost>
</local_segment>
<local_segment>
<event_id>51</event_id>
<event_id>72</event_id>
<event_id>70</event_id>
<event_id>84</event_id>
<event_id>96</event_id>
<event_id>53</event_id>
<event_id>66</event_id>
<event_id>98</event_id>
<event_id>57</event_id>
<event_id>58</event_id>
<event_id>79</event_id>
<event_id>55</event_id>
<event_id>52</event_id>
<event_id>60</event_id>
<event_id>89</event_id>
<event_id>61</event_id>
<event_id>83</event_id>
<event_id>69</event_id>
<event_id>97</event_id>
<event_id>65</event_id>
<event_id>88</event_id>
<event_id>74</event_id>
<event_id>93</event_id>
<event_id>71</event_id>
<event_id>95</event_id>
<event_id>59</event_id>
<event_id>67</event_id>
<event_id>86</event_id>
<event_id>87</event_id>
<event_id>81</event_id>
<event_id>68</event_id>
<event_id>73</event_id>
<event_id>78</event_id>
<event_id>64</event_id>
<event_id>77</event_id>
<event_id>62</event_id>
<event_id>82</event_id>
<event_id>94</event_id>
<event_id>75</event_id>
<event_id>91</event_id>
<event_id>100</event_id>
<event_id>54</event_id>
<event_id>85</event_id>
<event_id>99</event_id>
<event_id>90</event_id>
<event_id>92</event_id>
<event_id>63</event_id>
<event_id>56</event_id>
<event_id>80</event_id>
<event_id>76</event_id>
<dailyrate>25.050667</dailyrate>
<cost>2001.425903</cost>
</local_segment>
<local_segment>
<event_id>115</event_id>
<event_id>147</event_id>
<event_id>113</event_id>
<event_id>136</event_id>
<event_id>133</event_id>
<event_id>120</event_id>
<event_id>109</event_id>
<event_id>143</event_id>
<event_id>137</event_id>
<event_id>110</event_id>
<event_id>125</event_id>
<event_id>102</event_id>
<event_id>122</event_id>
<event_id>129</event_id>
<event_id>104</event_id>
<event_id>107</event_id>
<event_id>132</event_id>
<event_id>140</event_id>
<event_id>103</event_id>
<event_id>121</event_id>
<event_id>112</event_id>
<event_id>123</event_id>
<event_id>124</event_id>
<event_id>116</event_id>
<event_id>145</event_id>
<event_id>118</event_id>
<event_id>111</event_id>
<event_id>134</event_id>
<event_id>144</event_id>
<event_id>148</event_id>
<event_id>150</event_id>
<event_id>108</event_id>
<event_id>139</event_id>
<event_id>135</event_id>
<event_id>105</event_id>
<event_id>117</event_id>
<event_id>130</event_id>
<event_id>142</event_id>
<event_id>119</event_id>
<event_id>127</event_id>
<event_id>114</event_id>
<event_id>149</event_id>
<event_id>146</event_id>
<event_id>126</event_id>
<event_id>141</event_id>
<event_id>101</event_id>
<event_id>131</event_id>
<event_id>138</event_id>
<event_id>128</event_id>
<event_id>106</event_id>
<dailyrate>75.017334</dailyrate>
<cost>2417.026123</cost>
</local_segment>
<segmentcost>756.670468</segmentcost>
</time_segment>
<totalmodelcost>46901.386719</totalmodelcost>
</summarization>
